nptsne.libs/libgomp-f7e03b3e.so.1.0.0
nptsne/_full_version.txt
nptsne/__init__.pyi
nptsne/__init__.py
nptsne/_branch_name.txt
nptsne/example.py
nptsne/version.py
nptsne/_version.txt
nptsne/py.typed
nptsne/hsne_analysis/analysis_model.py
nptsne/hsne_analysis/__init__.pyi
nptsne/hsne_analysis/__init__.py
nptsne/libs/_nptsne.cpython-36m-x86_64-linux-gnu.so
nptsne-1.2.0.dist-info/METADATA
nptsne-1.2.0.dist-info/LICENSE.txt
nptsne-1.2.0.dist-info/WHEEL
nptsne-1.2.0.dist-info/RECORD
nptsne-1.2.0.dist-info/top_level.txt
