Metadata-Version: 2.1
Name: nptsne
Version: 1.2.0
Summary: The nptsne package is designed to export a number of python classes that wrap tSNE and HSNE
Home-page: https://biovault.github.io/nptsne
Author: Nicola Pezzotti, Thomas Höllt, Julian Thijssen, Baldur van Lew
Author-email: b.van_lew@lumc.nl
License: Apache-2
Project-URL: Tracker, https://github.com/biovault/nptsne/issues
Project-URL: Documentation, https://bldrvnlw.readthedocs.io
Project-URL: Source, https://github.com/biovault/nptsne
Keywords: tSNE HSNE embedding GPU
Platform: UNKNOWN
Classifier: Intended Audience :: Science/Research
Classifier: Intended Audience :: Developers
Classifier: License :: OSI Approved :: Apache Software License
Classifier: Topic :: Software Development
Classifier: Topic :: Scientific/Engineering
Classifier: Operating System :: Microsoft :: Windows
Classifier: Operating System :: MacOS :: MacOS X
Classifier: Operating System :: POSIX :: Linux
Classifier: Programming Language :: Python :: 3
Classifier: Programming Language :: Python :: 3.6
Classifier: Programming Language :: Python :: 3.7
Classifier: Programming Language :: Python :: 3.8
Classifier: Programming Language :: C++
Classifier: Typing :: Typed
License-File: LICENSE.txt
Requires-Dist: numpy (>="1.11.0")
